pyrisks/__init__.py
pyrisks/liquidity_risk.py
pyrisks-0.1.3.dist-info/METADATA
pyrisks-0.1.3.dist-info/WHEEL
pyrisks-0.1.3.dist-info/top_level.txt
pyrisks-0.1.3.dist-info/RECORD
