Metadata-Version: 2.1
Name: pyrisks
Version: 0.1.3
Summary: ...
Home-page: UNKNOWN
Author: Andres Felipe Rico, Diego Nicolas Rozo, Juan Camilo Martinez, Nicolas Ricardo Lopez, Lucas Gómez Tobón, William Andres Sanchez
Author-email: lucasgomeztobon@gmail.com, 
License: MIT
Platform: UNKNOWN
Classifier: Intended Audience :: Developers
Classifier: License :: OSI Approved :: MIT License
Classifier: Programming Language :: Python
Classifier: Programming Language :: Python :: 3
Classifier: Programming Language :: Python :: 3.6
Classifier: Programming Language :: Python :: 3.7
Classifier: Programming Language :: Python :: 3.8
Classifier: Programming Language :: Python :: 3.9
Classifier: Operating System :: OS Independent
Requires-Dist: numpy
Requires-Dist: pandas
